image_array_and_histogram/__init__.py
image_array_and_histogram/main.py
image_array_and_histogram-1.1.1.dist-info/LICENSE
image_array_and_histogram-1.1.1.dist-info/METADATA
image_array_and_histogram-1.1.1.dist-info/WHEEL
image_array_and_histogram-1.1.1.dist-info/top_level.txt
image_array_and_histogram-1.1.1.dist-info/RECORD
