Metadata-Version: 2.1
Name: image_array_and_histogram
Version: 1.1.1
Summary: Utilities to get arrays & histograms from grayscale images and build images from arrays.
Home-page: https://github.com/rishi-chauhan/my-packages.git
Author: Rishi Raj Singh Chauhan
Author-email: 
License: MIT
Project-URL: Homepage, https://github.com/rishi-chauhan/my-packages
Project-URL: Issue Tracker, https://github.com/rishi-chauhan/my-packages/issues
Keywords: image,histogram,numpy,pillow,grayscale
Classifier: Programming Language :: Python :: 3
Classifier: Programming Language :: Python :: 3 :: Only
Classifier: License :: OSI Approved :: MIT License
Classifier: Operating System :: OS Independent
Classifier: Topic :: Multimedia :: Graphics
Classifier: Topic :: Scientific/Engineering :: Image Processing
Requires-Python: >=3.8
License-File: LICENSE
Requires-Dist: numpy>=1.20
Requires-Dist: Pillow>=9.0
Provides-Extra: dev
Requires-Dist: pytest>=7; extra == "dev"
Requires-Dist: build; extra == "dev"
